AUTHORS.txt
MANIFEST.in
README.rst
THANKS.txt
TODO.txt
requirements.stable.txt
requirements.txt
setup.py
tasks.py
.idea/codeStyleSettings.xml
.idea/encodings.xml
.idea/misc.xml
.idea/modules.xml
.idea/vcs.xml
.idea/workspace.xml
.idea/inspectionProfiles/Project_Default.xml
.idea/inspectionProfiles/profiles_settings.xml
.idea/scopes/scope_settings.xml
bash/bash_aliases
bash/bash_aliases~
bash/build_env.sh
bash/ddt
bash/linod.sh
bash/make_snapshot.sh
bash/make_snapshot.sh~
bash/pull.sh
bash/run_linod.sh
bash/run_linod.sh~
lino/__init__.py
lino/ad.py
lino/hello.py
lino/setup_info.py
lino.egg-info/PKG-INFO
lino.egg-info/SOURCES.txt
lino.egg-info/dependency_links.txt
lino.egg-info/not-zip-safe
lino.egg-info/requires.txt
lino.egg-info/top_level.txt
lino/api/__init__.py
lino/api/ad.py
lino/api/dd.py
lino/api/doctest.py
lino/api/rt.py
lino/api/selenium.py
lino/api/shell.py
lino/core/__init__.py
lino/core/actions.py
lino/core/actors.py
lino/core/boundaction.py
lino/core/choicelists.py
lino/core/constants.py
lino/core/dashboard.py
lino/core/dbtables.py
lino/core/dbutils.py
lino/core/ddh.py
lino/core/diff.py
lino/core/elems.py
lino/core/exceptions.py
lino/core/fields.py
lino/core/frames.py
lino/core/gfks.py
lino/core/inject.py
lino/core/kernel.py
lino/core/keyboard.py
lino/core/layouts.py
lino/core/menus.py
lino/core/merge.py
lino/core/model.py
lino/core/permissions.py
lino/core/plugin.py
lino/core/renderer.py
lino/core/requests.py
lino/core/roles.py
lino/core/signals.py
lino/core/site.py
lino/core/store.py
lino/core/tablerequest.py
lino/core/tables.py
lino/core/urls.py
lino/core/user_types.py
lino/core/userprefs.py
lino/core/utils.py
lino/core/views.py
lino/core/workflows.py
lino/core/auth/__init__.py
lino/core/auth/backends.py
lino/core/auth/middleware.py
lino/core/auth/utils.py
lino/fake_migrations/__init__.py
lino/history/__init__.py
lino/history/luc201212.py
lino/history/show.py
lino/invlib/__init__.py
lino/invlib/ns.py
lino/invlib/tasks.py
lino/mixins/__init__.py
lino/mixins/bleached.py
lino/mixins/dupable.py
lino/mixins/duplicable.py
lino/mixins/human.py
lino/mixins/periods.py
lino/mixins/polymorphic.py
lino/mixins/printable.py
