Metadata-Version: 1.1
Name: lino
Version: 17.10.1
Summary: A framework for writing desktop-like web applications using Django and ExtJS
Home-page: http://www.lino-framework.org
Author: Luc Saffre
Author-email: luc.saffre@gmail.com
License: BSD License
Platform: UNKNOWN
Classifier: Programming Language :: Python
Classifier: Programming Language :: Python :: 2
Classifier: Programming Language :: Python :: 3
Classifier: Development Status :: 5 - Production/Stable
Classifier: Environment :: Web Environment
Classifier: Framework :: Django
Classifier: Intended Audience :: Developers
Classifier: Intended Audience :: System Administrators
Classifier: License :: OSI Approved :: BSD License
Classifier: Natural Language :: English
Classifier: Natural Language :: French
Classifier: Natural Language :: German
Classifier: Operating System :: OS Independent
Classifier: Topic :: Database :: Front-Ends
Classifier: Topic :: Office/Business
Classifier: Topic :: Software Development :: Libraries :: Application Frameworks
Obsoletes: djangosite
Obsoletes: north
